atlas_anndata/__init__.py
atlas_anndata/anndata_config.py
atlas_anndata/anndata_ops.py
atlas_anndata/config_schema.yaml
atlas_anndata/funcs.py
atlas_anndata/strings.py
atlas_anndata/util.py
atlas_anndata/data/bundles/E-MTAB-6077/E-MTAB-6077.project.h5ad
atlas_anndata/data/bundles/E-MTAB-6077/MANIFEST
atlas_anndata/data/bundles/E-MTAB-6077/anndata-config.yaml
atlas_anndata/snakemake/README
atlas_anndata/snakemake/cell_metadata_from_magetab/workflow/E-ANND-1.metadata.tsv
atlas_anndata/snakemake/cell_metadata_from_magetab/workflow/Snakefile
atlas_anndata/snakemake/cell_metadata_from_magetab/workflow/envs/atlas-experiment-metadata.yml
atlas_anndata-0.1.9.data/scripts/make_bundle_from_anndata
atlas_anndata-0.1.9.data/scripts/validate_anndata_with_config
atlas_anndata-0.1.9.dist-info/LICENSE
atlas_anndata-0.1.9.dist-info/METADATA
atlas_anndata-0.1.9.dist-info/WHEEL
atlas_anndata-0.1.9.dist-info/top_level.txt
atlas_anndata-0.1.9.dist-info/RECORD
