Metadata-Version: 2.1
Name: atlas-anndata
Version: 0.1.9
Summary: Functions for preparing annData files for experiment inclusion in Single cell Expression Atlas
Home-page: https://github.com/ebi-gene-expression-group/atlas-anndata
Author: Jonathan Manning
Author-email: jmanning@ebi.ac.uk
License: Apache Software License
Classifier: Programming Language :: Python :: 3
Classifier: License :: OSI Approved :: Apache Software License
Classifier: Operating System :: OS Independent
Classifier: Topic :: Scientific/Engineering :: Bio-Informatics
Requires-Python: <3.9,>=3.6
License-File: LICENSE
Requires-Dist: scanpy-scripts (>1.1.5)
Requires-Dist: PyYAML
Requires-Dist: click
Requires-Dist: jsonschema
Requires-Dist: snakemake
